CHANGES.rst
CONTRIBUTORS.rst
MANIFEST.in
README.rst
setup.cfg
setup.py
docs/LICENSE.GPL
docs/LICENSE.rst
docs/Makefile
docs/conf.py
docs/export-import.rst
docs/index.rst
docs/nuts-bolts.rst
docs/restrictedpython.rst
docs/tutorial.rst
docs/images/ambidexterity_editor.png
docs/images/ambidexterity_editor_dropdown.png
docs/images/ambidexterity_editor_field_dropdown.png
docs/images/default_editor.png
docs/images/default_traceback.png
docs/images/default_view.png
docs/images/dexterity1.png
docs/images/updated_view.png
docs/images/validator_edit.png
docs/images/view_editor.png
src/collective/__init__.py
src/collective.ambidexterity.egg-info/PKG-INFO
src/collective.ambidexterity.egg-info/SOURCES.txt
src/collective.ambidexterity.egg-info/dependency_links.txt
src/collective.ambidexterity.egg-info/entry_points.txt
src/collective.ambidexterity.egg-info/namespace_packages.txt
src/collective.ambidexterity.egg-info/not-zip-safe
src/collective.ambidexterity.egg-info/requires.txt
src/collective.ambidexterity.egg-info/top_level.txt
src/collective/ambidexterity/__init__.py
src/collective/ambidexterity/audit.py
src/collective/ambidexterity/configure.zcml
src/collective/ambidexterity/default_script.py
src/collective/ambidexterity/interfaces.py
src/collective/ambidexterity/interpreter.py
src/collective/ambidexterity/models.py
src/collective/ambidexterity/setuphandlers.py
src/collective/ambidexterity/subscribers.py
src/collective/ambidexterity/testing.py
src/collective/ambidexterity/utilities.py
src/collective/ambidexterity/validator_script.py
src/collective/ambidexterity/view.py
src/collective/ambidexterity/vocabulary_script.py
src/collective/ambidexterity/browser/__init__.py
src/collective/ambidexterity/browser/configure.zcml
src/collective/ambidexterity/browser/editor.js
src/collective/ambidexterity/browser/editor.pt
src/collective/ambidexterity/browser/editor.py
src/collective/ambidexterity/browser/import_export.py
src/collective/ambidexterity/locales/collective.ambidexterity.pot
src/collective/ambidexterity/locales/update.sh
src/collective/ambidexterity/profiles/default/browserlayer.xml
src/collective/ambidexterity/profiles/default/controlpanel.xml
src/collective/ambidexterity/profiles/default/metadata.xml
src/collective/ambidexterity/profiles/default/registry.xml
src/collective/ambidexterity/profiles/testing/types.xml
src/collective/ambidexterity/profiles/testing/types/simple_test_type.xml
