Metadata-Version: 1.1
Name: collective.ambidexterity
Version: 1.0
Summary: TTW support for Dexterity
Home-page: https://pypi.python.org/pypi/collective.ambidexterity
Author: Steve McMahon
Author-email: steve@dcn.org
License: GPL version 2
Keywords: Python Plone
Platform: UNKNOWN
Classifier: Environment :: Web Environment
Classifier: Framework :: Plone
Classifier: Framework :: Plone :: 5.0
Classifier: Programming Language :: Python
Classifier: Programming Language :: Python :: 2.7
Classifier: Operating System :: OS Independent
Classifier: License :: OSI Approved :: GNU General Public License v2 (GPLv2)
